bioimageio_chatbot/__init__.py
bioimageio_chatbot/__main__.py
bioimageio_chatbot/chatbot.py
bioimageio_chatbot/evaluation.py
bioimageio_chatbot/gpts_action.py
bioimageio_chatbot/jsonschema_pydantic.py
bioimageio_chatbot/knowledge_base.py
bioimageio_chatbot/quota.py
bioimageio_chatbot/tools.py
bioimageio_chatbot/utils.py
bioimageio_chatbot/chatbot_extensions/__init__.py
bioimageio_chatbot/chatbot_extensions/bia_extension.py
bioimageio_chatbot/chatbot_extensions/biii_extension.py
bioimageio_chatbot/chatbot_extensions/docs_extension.py
bioimageio_chatbot/chatbot_extensions/hpa_extension.py
bioimageio_chatbot/chatbot_extensions/image_sc_extension.py
bioimageio_chatbot/chatbot_extensions/vision_extension.py
bioimageio_chatbot/chatbot_extensions/web_search_extension/__init__.py
bioimageio_chatbot/chatbot_extensions/web_search_extension/langchain_websearch.py
bioimageio_chatbot/static/bioimage-model-zoo-extension.imjoy.html
bioimageio_chatbot/static/imagej-js-extension.imjoy.html
bioimageio_chatbot/static/index.html
bioimageio_chatbot/static/pyodide-worker.js
bioimageio_chatbot/static/worker-manager.js
bioimageio_chatbot-0.2.13.dist-info/LICENSE
bioimageio_chatbot-0.2.13.dist-info/METADATA
bioimageio_chatbot-0.2.13.dist-info/WHEEL
bioimageio_chatbot-0.2.13.dist-info/top_level.txt
bioimageio_chatbot-0.2.13.dist-info/RECORD
