Metadata-Version: 2.1
Name: bioimageio-chatbot
Version: 0.2.13
Summary: Your Personal Assistant in Computational BioImaging.
License-File: LICENSE
Requires-Dist: schema-agents>=0.1.59
Requires-Dist: hypha-rpc>=0.20.38
Requires-Dist: requests
Requires-Dist: pypdf
Requires-Dist: pillow
Requires-Dist: matplotlib
Requires-Dist: hypha>=0.20.38.post19
Requires-Dist: tqdm
Requires-Dist: aiofiles
Requires-Dist: langchain>=0.1.6
Requires-Dist: beautifulsoup4
Requires-Dist: pandas
Requires-Dist: duckduckgo-search>=6.1.5
Requires-Dist: rank-bm25
Requires-Dist: langchain-openai
Requires-Dist: langchain-core>=0.1.31
Requires-Dist: langchain-community>=0.0.27
Requires-Dist: html2text
